drf_fileupload/__init__.py
drf_fileupload/apps.py
drf_fileupload/models.py
drf_fileupload/serializers.py
drf_fileupload/urls.py
drf_fileupload/views.py
drf_fileupload/migrations/0001_initial.py
drf_fileupload/migrations/__init__.py
drf_fileupload/version/version.json
drf_fileupload_api-1.0.1.dist-info/METADATA
drf_fileupload_api-1.0.1.dist-info/WHEEL
drf_fileupload_api-1.0.1.dist-info/top_level.txt
drf_fileupload_api-1.0.1.dist-info/RECORD
