Metadata-Version: 2.1
Name: drf-fileupload-api
Version: 1.0.1
Summary: A file upload application for DjangoRestFramework
Home-page: https://github.com/suqingdong/drf_fileupload
Author: suqingdong
Author-email: suqingdong1114@gmail.com
License: BSD License
Platform: UNKNOWN
Classifier: Framework :: Django
Classifier: Framework :: Django :: 4.1
Classifier: Operating System :: OS Independent
Classifier: Intended Audience :: Developers
Classifier: License :: OSI Approved :: BSD License
Classifier: Programming Language :: Python
Classifier: Programming Language :: Python :: 3
Classifier: Programming Language :: Python :: 3 :: Only
Classifier: Programming Language :: Python :: 3.8
Classifier: Programming Language :: Python :: 3.9
Classifier: Topic :: Software Development :: Libraries
Requires-Dist: python-magic
Requires-Dist: humanfriendly
Requires-Dist: djangorestframework
